dumbo/__init__.py
dumbo/api.py
dumbo/middleware.py
dumbo/response.py
dumbo_marek/__init__.py
dumbo_marek/api.py
dumbo_marek/middleware.py
dumbo_marek/orm.py
dumbo_marek/response.py
dumbo_marek-0.0.6.dist-info/METADATA
dumbo_marek-0.0.6.dist-info/WHEEL
dumbo_marek-0.0.6.dist-info/top_level.txt
dumbo_marek-0.0.6.dist-info/RECORD
