Metadata-Version: 2.1
Name: dumbo-marek
Version: 0.0.6
Summary: Dumbo Python Web Framework built for learning purposes.
Author: Marek Sedlacek
Author-email: marek.sedlacek.sk@gmail.com
License: MIT
Classifier: Programming Language :: Python :: 3.10
Requires-Python: >=3.10.0
Requires-Dist: Jinja2 (==3.1.2)
Requires-Dist: parse (==1.12.1)
Requires-Dist: requests (==2.28.1)
Requires-Dist: requests-wsgi-adapter (==0.4.1)
Requires-Dist: WebOb (==1.8.5)
Requires-Dist: whitenoise (==4.1.4)
